{
  "webmall_1_nlweb" : {
    "mappings" : {
      "properties" : {
        "category" : {
          "type" : "text",
          "fields" : {
            "hierarchy" : {
              "type" : "text",
              "analyzer" : "category_analyzer"
            },
            "keyword" : {
              "type" : "keyword",
              "ignore_above" : 256
            }
          },
          "analyzer" : "product_analyzer"
        },
        "composite_embedding" : {
          "type" : "dense_vector",
          "dims" : 1536,
          "index" : true,
          "similarity" : "cosine"
        },
        "content_embedding" : {
          "type" : "dense_vector",
          "dims" : 1536,
          "index" : true,
          "similarity" : "cosine"
        },
        "created_at" : {
          "type" : "date"
        },
        "description" : {
          "type" : "text",
          "analyzer" : "product_analyzer"
        },
        "price" : {
          "type" : "float"
        },
        "product_id" : {
          "type" : "keyword"
        },
        "related_products" : {
          "type" : "keyword"
        },
        "schema_org" : {
          "properties" : {
            "@context" : {
              "type" : "text",
              "fields" : {
                "keyword" : {
                  "type" : "keyword",
                  "ignore_above" : 256
                }
              }
            },
            "@type" : {
              "type" : "text",
              "fields" : {
                "keyword" : {
                  "type" : "keyword",
                  "ignore_above" : 256
                }
              }
            },
            "brand" : {
              "properties" : {
                "@type" : {
                  "type" : "text",
                  "fields" : {
                    "keyword" : {
                      "type" : "keyword",
                      "ignore_above" : 256
                    }
                  }
                },
                "name" : {
                  "type" : "text",
                  "fields" : {
                    "keyword" : {
                      "type" : "keyword",
                      "ignore_above" : 256
                    }
                  }
                }
              }
            },
            "category" : {
              "type" : "text",
              "fields" : {
                "keyword" : {
                  "type" : "keyword",
                  "ignore_above" : 256
                }
              }
            },
            "description" : {
              "type" : "text",
              "fields" : {
                "keyword" : {
                  "type" : "keyword",
                  "ignore_above" : 256
                }
              }
            },
            "identifier" : {
              "properties" : {
                "@type" : {
                  "type" : "text",
                  "fields" : {
                    "keyword" : {
                      "type" : "keyword",
                      "ignore_above" : 256
                    }
                  }
                },
                "name" : {
                  "type" : "text",
                  "fields" : {
                    "keyword" : {
                      "type" : "keyword",
                      "ignore_above" : 256
                    }
                  }
                },
                "value" : {
                  "type" : "text",
                  "fields" : {
                    "keyword" : {
                      "type" : "keyword",
                      "ignore_above" : 256
                    }
                  }
                }
              }
            },
            "image" : {
              "type" : "text",
              "fields" : {
                "keyword" : {
                  "type" : "keyword",
                  "ignore_above" : 256
                }
              }
            },
            "name" : {
              "type" : "text",
              "fields" : {
                "keyword" : {
                  "type" : "keyword",
                  "ignore_above" : 256
                }
              }
            },
            "offers" : {
              "properties" : {
                "@type" : {
                  "type" : "text",
                  "fields" : {
                    "keyword" : {
                      "type" : "keyword",
                      "ignore_above" : 256
                    }
                  }
                },
                "availability" : {
                  "type" : "text",
                  "fields" : {
                    "keyword" : {
                      "type" : "keyword",
                      "ignore_above" : 256
                    }
                  }
                },
                "itemCondition" : {
                  "type" : "text",
                  "fields" : {
                    "keyword" : {
                      "type" : "keyword",
                      "ignore_above" : 256
                    }
                  }
                },
                "price" : {
                  "type" : "text",
                  "fields" : {
                    "keyword" : {
                      "type" : "keyword",
                      "ignore_above" : 256
                    }
                  }
                },
                "priceCurrency" : {
                  "type" : "text",
                  "fields" : {
                    "keyword" : {
                      "type" : "keyword",
                      "ignore_above" : 256
                    }
                  }
                },
                "priceValidUntil" : {
                  "type" : "text",
                  "fields" : {
                    "keyword" : {
                      "type" : "keyword",
                      "ignore_above" : 256
                    }
                  }
                },
                "url" : {
                  "type" : "text",
                  "fields" : {
                    "keyword" : {
                      "type" : "keyword",
                      "ignore_above" : 256
                    }
                  }
                }
              }
            },
            "url" : {
              "type" : "text",
              "fields" : {
                "keyword" : {
                  "type" : "keyword",
                  "ignore_above" : 256
                }
              }
            }
          }
        },
        "title" : {
          "type" : "text",
          "fields" : {
            "keyword" : {
              "type" : "keyword",
              "ignore_above" : 256
            }
          },
          "analyzer" : "product_analyzer"
        },
        "title_embedding" : {
          "type" : "dense_vector",
          "dims" : 1536,
          "index" : true,
          "similarity" : "cosine"
        },
        "updated_at" : {
          "type" : "date"
        },
        "url" : {
          "type" : "keyword"
        }
      }
    }
  }
}
